dj_magister/__init__.py
dj_magister/access_manager.py
dj_magister/apps.py
dj_magister/models.py
dj_magister/core/__init__.py
dj_magister/core/exceptions.py
dj_magister/core/models.py
dj_magister/core/schema_access.py
dj_magister/core/utils.py
dj_magister/core/check_permission/__init__.py
dj_magister/core/check_permission/check_direct_subject_rel.py
dj_magister/core/check_permission/check_inherited_subject_rel.py
dj_magister/core/check_permission/check_permission.py
dj_magister/core/check_permission/utils.py
dj_magister/core/lookup_object_relation/__init__.py
dj_magister/core/lookup_object_relation/lookup_relations.py
dj_magister/core/lookup_resources/__init__.py
dj_magister/core/lookup_resources/lookup_resources.py
dj_magister/core/lookup_resources/lookup_resources_direct_rel.py
dj_magister/core/lookup_resources/lookup_resources_inherit_rel.py
dj_magister/core/lookup_subjects/__init__.py
dj_magister/core/lookup_subjects/lookup_subjects.py
dj_magister/core/lookup_subjects/lookup_subjects_direct_rel.py
dj_magister/core/lookup_subjects/lookup_subjects_inherit_rel.py
dj_magister/core/relationship_writer/__init__.py
dj_magister/core/relationship_writer/writer.py
dj_magister/management/commands/__init__.py
dj_magister/management/commands/add.py
dj_magister/management/commands/helper.py
dj_magister/management/commands/permission.py
dj_magister/migrations/0001_initial.py
dj_magister/migrations/__init__.py
dj_magister-0.0.2.dist-info/licenses/LICENSE
dj_magister-0.0.2.dist-info/METADATA
dj_magister-0.0.2.dist-info/WHEEL
dj_magister-0.0.2.dist-info/top_level.txt
dj_magister-0.0.2.dist-info/RECORD
